fast_api_jwt_middleware/__init__.py
fast_api_jwt_middleware/context_holder.py
fast_api_jwt_middleware/auth/__init__.py
fast_api_jwt_middleware/auth/auth_middleware.py
fast_api_jwt_middleware/auth/multi_provider_auth_middleware.py
fast_api_jwt_middleware/cache/__init__.py
fast_api_jwt_middleware/cache/cache_protocol_contract.py
fast_api_jwt_middleware/cache/token_cache.py
fast_api_jwt_middleware/cache/token_cache_singleton.py
fast_api_jwt_middleware/logger/__init__.py
fast_api_jwt_middleware/logger/logger_protocol_contract.py
fast_api_jwt_middleware/oidc/__init__.py
fast_api_jwt_middleware/oidc/oidc_helper.py
fast_api_jwt_middleware/oidc/oidc_providers.py
fast_api_jwt_middleware/utils/__init__.py
fast_api_jwt_middleware/utils/wrapper.py
fast_api_jwt_middleware-1.0.1.dist-info/LICENSE
fast_api_jwt_middleware-1.0.1.dist-info/METADATA
fast_api_jwt_middleware-1.0.1.dist-info/WHEEL
fast_api_jwt_middleware-1.0.1.dist-info/top_level.txt
fast_api_jwt_middleware-1.0.1.dist-info/RECORD
