Metadata-Version: 2.2
Name: fast-api-jwt-middleware
Version: 1.0.1
Summary: A FastAPI middleware for JWT-based authentication with support for multiple providers.
Author-email: csheader <csheaderusa@gmail.com>
License: MIT License
Project-URL: Homepage, https://github.com/csheader/fast-api-oidc
Project-URL: Issues, https://github.com/csheader/fast-api-oidc/issues
Classifier: Development Status :: 5 - Production/Stable
Classifier: Intended Audience :: Developers
Classifier: License :: OSI Approved :: MIT License
Classifier: Programming Language :: Python :: 3
Classifier: Programming Language :: Python :: 3.10
Classifier: Programming Language :: Python :: 3.11
Classifier: Programming Language :: Python :: 3.12
Classifier: Programming Language :: Python :: 3.13
Classifier: Framework :: FastAPI
Requires-Python: >=3.10
License-File: LICENSE
Requires-Dist: fastapi
Requires-Dist: starlette
Requires-Dist: cachetools
Requires-Dist: requests
Requires-Dist: pyjwt>=2.8.0
Requires-Dist: cryptography
